README.rst
setup.py
term2image/TermEmulator.py
term2image/__init__.py
term2image/fonts.py
term2image.egg-info/PKG-INFO
term2image.egg-info/SOURCES.txt
term2image.egg-info/dependency_links.txt
term2image.egg-info/entry_points.txt
term2image.egg-info/requires.txt
term2image.egg-info/top_level.txt